{"advanced_custom-resolution.md":"D0KJXmwE","advanced_debugging.md":"D_p1xa1V","advanced_index.md":"CmU5huJp","advanced_typescript.md":"DoPlGf_O","api_index.md":"DPjcbWFp","api_smart-row-array.md":"DNxl79L-","api_smart-row.md":"DbP1WZ9w","api_strategies.md":"DPdlDv7F","api_table-config.md":"B4HzEBFi","api_table-methods.md":"C0oEnm7A","concepts_header-mapping.md":"BNAPSqn3","concepts_pagination-strategies.md":"CncI1P9o","concepts_strategies.md":"D6mQafhz","concepts_table-anatomy.md":"D2LMEc6O","examples_ag-grid.md":"C8bwI7q7","examples_basic.md":"C6VRNI0J","examples_index.md":"DftJF15R","examples_infinite-scroll.md":"mfOtNmr6","examples_mui-datagrid.md":"aTdK4p_I","examples_pagination.md":"CG7uZ0KQ","guide_configuration.md":"BnZX3VwR","guide_core-concepts.md":"BkFLeQH5","guide_debugging.md":"DpVc610N","guide_getting-started.md":"DtX_wRBa","guide_recipes.md":"CMKR3IQv","index.md":"aaJSvS_J","lab_index.md":"BzGLWDNI","preset_development.md":"Cu39Hv9P","preset_template.md":"pJ3Jc7_8","recipes_custom-strategies.md":"0CuDk695","recipes_data-scraping.md":"BLpwjYf9","recipes_index.md":"B8V4xMKV","recipes_performance.md":"2rrA310q","troubleshooting.md":"DXk3_9jQ"}
